venusclient/__init__.py
venusclient/exceptions.py
venusclient/i18n.py
venusclient/shell.py
venusclient/version.py
venusclient/common/__init__.py
venusclient/common/base.py
venusclient/common/cliutils.py
venusclient/common/http.py
venusclient/common/httpclient.py
venusclient/common/utils.py
venusclient/common/apiclient/__init__.py
venusclient/common/apiclient/base.py
venusclient/common/apiclient/exceptions.py
venusclient/osc/__init__.py
venusclient/osc/plugin.py
venusclient/osc/v1/__init__.py
venusclient/tests/__init__.py
venusclient/v1/__init__.py
venusclient/v1/analyse.py
venusclient/v1/analyse_shell.py
venusclient/v1/anomaly.py
venusclient/v1/anomaly_shell.py
venusclient/v1/basemodels.py
venusclient/v1/client.py
venusclient/v1/config.py
venusclient/v1/config_shell.py
venusclient/v1/search.py
venusclient/v1/search_shell.py
venusclient/v1/shell.py
python_venusclient-2.5.0.dist-info/AUTHORS
python_venusclient-2.5.0.dist-info/LICENSE
python_venusclient-2.5.0.dist-info/METADATA
python_venusclient-2.5.0.dist-info/WHEEL
python_venusclient-2.5.0.dist-info/entry_points.txt
python_venusclient-2.5.0.dist-info/pbr.json
python_venusclient-2.5.0.dist-info/top_level.txt
python_venusclient-2.5.0.dist-info/RECORD
